{
  "publicPath": "https://yiranni.github.io/master-thesis/_nuxt/",
  "all": [
    "../server/index.spa.html",
    "../server/index.ssr.html",
    "004d6765b851bbe856e8.js",
    "6b958a0539ca8f1b95a1.js",
    "8f762cbe7a4a96469ce2.js",
    "LICENSES",
    "ae5edfd4a045906f5a5e.js",
    "c4388af5d0d36905bbfc.js",
    "cb29d40efca0f98d54f9.js",
    "f18ab47b0c8600674e6a.js",
    "fa0c48a5b5a17ed787cd.js",
    "fonts/535877f.woff",
    "fonts/732389d.ttf",
    "img/062632c.png",
    "img/234aed6.png",
    "img/5549de3.png",
    "img/9b8c32c.png",
    "img/cbd0434.svg",
    "img/d0ef5f3.png"
  ],
  "initial": [
    "fa0c48a5b5a17ed787cd.js",
    "f18ab47b0c8600674e6a.js",
    "c4388af5d0d36905bbfc.js",
    "8f762cbe7a4a96469ce2.js"
  ],
  "async": [
    "004d6765b851bbe856e8.js",
    "6b958a0539ca8f1b95a1.js",
    "ae5edfd4a045906f5a5e.js",
    "cb29d40efca0f98d54f9.js"
  ],
  "modules": {
    "21115365": [
      3
    ],
    "21309240": [
      7,
      11,
      12
    ],
    "21723071": [
      7,
      11,
      12
    ],
    "24181846": [
      8,
      18,
      16,
      14,
      13,
      15
    ],
    "24421995": [
      3
    ],
    "37232115": [
      8,
      18,
      16,
      14,
      13,
      15
    ],
    "41213026": [
      3
    ],
    "43775268": [
      9
    ],
    "53326016": [
      3
    ],
    "54860176": [
      3
    ],
    "60335636": [
      9
    ],
    "64955523": [
      3
    ],
    "66718735": [
      8,
      18,
      16,
      14,
      13,
      15
    ],
    "66725925": [
      8,
      18,
      16,
      14,
      13,
      15
    ],
    "67225604": [
      7,
      11,
      12
    ],
    "69779836": [
      3
    ],
    "73667556": [
      8,
      18,
      16,
      14,
      13,
      15
    ],
    "75776246": [
      3
    ],
    "75802241": [
      3
    ],
    "77176743": [
      9
    ],
    "79539364": [
      6
    ],
    "95987740": [
      8,
      18,
      16,
      14,
      13,
      15
    ],
    "3133e440": [
      9
    ],
    "33d3effc": [
      4,
      17
    ],
    "4254357e": [
      9
    ],
    "457d8f0b": [
      9
    ],
    "dbbe4c7e": [
      9
    ],
    "9539280a": [
      9
    ],
    "478b395a": [
      9
    ],
    "d4a5e948": [
      9
    ],
    "f92319a8": [
      7,
      11,
      12
    ],
    "f160fa34": [
      9
    ],
    "8fb4fb04": [
      9
    ],
    "7c5baa4b": [
      9
    ],
    "73bd9360": [
      9
    ],
    "4e2bac0e": [
      7,
      11,
      12
    ],
    "0abfa5b1": [
      7,
      11,
      12
    ],
    "0ef7d83b": [
      4,
      17
    ],
    "0a412c78": [
      4,
      17
    ],
    "ac37c7fc": [
      4,
      17
    ],
    "15b8f754": [
      4,
      17
    ],
    "565316f1": [
      4,
      17
    ],
    "005e4ba8": [
      4,
      17
    ],
    "5b76e56b": [
      4,
      17
    ],
    "407f8b6e": [
      4,
      17
    ],
    "64de602c": [
      4,
      17
    ],
    "1e0f5b72": [
      4,
      17
    ],
    "01af6f88": [
      4,
      17
    ],
    "5a4248d4": [
      4,
      17
    ],
    "20ea9224": [
      4,
      17
    ],
    "1ba1ea9a": [
      4,
      17
    ],
    "59de897e": [
      4,
      17
    ],
    "71e68397": [
      4,
      17
    ],
    "ca13c220": [
      4,
      17
    ],
    "3d09eea6": [
      4,
      17
    ],
    "79f64cd1": [
      4,
      17
    ],
    "5dc82a18": [
      4,
      17
    ],
    "30d615ff": [
      4,
      17
    ],
    "66c2c462": [
      4,
      17
    ],
    "07312385": [
      4,
      17
    ],
    "486ad2e8": [
      4,
      17
    ],
    "cc45d946": [
      4,
      17
    ],
    "74de3596": [
      9
    ],
    "846a5272": [
      9
    ],
    "3e70e962": [
      9
    ],
    "123b06df": [
      9
    ],
    "07354eb8": [
      9
    ],
    "0bf7c588": [
      9
    ],
    "769f6e34": [
      9
    ],
    "07bd5788": [
      7,
      11,
      12
    ],
    "9cf54ff0": [
      9
    ],
    "1073fcdc": [
      9
    ],
    "b8bfebd0": [
      7,
      11,
      12
    ],
    "8593db8e": [
      9
    ],
    "5524b5be": [
      9
    ],
    "8d965ae2": [
      9
    ],
    "374dace0": [
      9
    ],
    "863123f4": [
      9
    ],
    "60be0697": [
      9
    ],
    "0de5b3a0": [
      9
    ],
    "5beb0a92": [
      9
    ],
    "73ea86e8": [
      9
    ],
    "11eb9ded": [
      9
    ],
    "c02df074": [
      9
    ],
    "89a19770": [
      7,
      11,
      12
    ],
    "3e9fb5fe": [
      7,
      11,
      12
    ],
    "5077f9d4": [
      7,
      11,
      12
    ],
    "13dccacf": [
      7,
      11,
      12
    ],
    "4441e6a9": [
      9
    ],
    "56795b63": [
      9
    ],
    "7b406aa5": [
      9
    ],
    "496d9920": [
      9
    ],
    "6482fa57": [
      9
    ],
    "886852bc": [
      9
    ],
    "34e8c71b": [
      9
    ],
    "5a0a993d": [
      9
    ],
    "5330e7b8": [
      9
    ],
    "afddf34e": [
      9
    ],
    "716c30f2": [
      9
    ],
    "1068e823": [
      9
    ],
    "e67debac": [
      9
    ],
    "40e5e7f7": [
      9
    ],
    "1ab2cd4b": [
      9
    ],
    "109f5a48": [
      9
    ],
    "29dc1880": [
      9
    ],
    "0e5a0c44": [
      9
    ],
    "07d58849": [
      9
    ],
    "95f7c108": [
      9
    ],
    "2c889ee8": [
      9
    ],
    "9282d8ca": [
      9
    ],
    "76d07b50": [
      9
    ],
    "fb608a86": [
      9
    ],
    "5fcdd1ee": [
      9
    ],
    "43bdc86c": [
      9
    ],
    "dbc52932": [
      9
    ],
    "dbc9b4e8": [
      9
    ],
    "e5fbc4de": [
      9
    ],
    "975a08ce": [
      9
    ],
    "73c27a18": [
      9
    ],
    "b731b29e": [
      9
    ],
    "6cbb3572": [
      9
    ],
    "3b062a1c": [
      7,
      11,
      12
    ],
    "40a07a08": [
      7,
      11,
      12
    ],
    "09fd080a": [
      7,
      11,
      12
    ],
    "b401a494": [
      7,
      11,
      12
    ],
    "8e8db6d6": [
      7,
      11,
      12
    ],
    "66bc616d": [
      9
    ],
    "290a67fa": [
      9
    ],
    "70fd026a": [
      9
    ],
    "4631ed51": [
      9
    ],
    "0e5eec1c": [
      9
    ],
    "35a5e924": [
      9
    ],
    "7938bb22": [
      4,
      17
    ],
    "2bfa9c0a": [
      4,
      17
    ],
    "1dfbca46": [
      4,
      17
    ],
    "6cb116ed": [
      4,
      17
    ],
    "541c64bf": [
      4,
      17
    ],
    "77f33f60": [
      9
    ],
    "d9223e72": [
      9
    ],
    "fb1b8fce": [
      9
    ],
    "2c7579b7": [
      9
    ],
    "6f17aa32": [
      9
    ],
    "dbd2cc54": [
      9
    ],
    "fd81c3a6": [
      9
    ],
    "4a0c55cb": [
      9
    ],
    "4fd968fc": [
      9
    ],
    "3dbaa52a": [
      9
    ],
    "0f09c074": [
      9
    ],
    "6bb82237": [
      9
    ],
    "03bf29be": [
      7,
      11,
      12
    ],
    "56098c74": [
      7,
      11,
      12
    ],
    "e69863ea": [
      7,
      11,
      12
    ],
    "600bed5a": [
      7,
      11,
      12
    ],
    "04057fd8": [
      7,
      11,
      12
    ],
    "2b15f32f": [
      7,
      11,
      12
    ],
    "cb939cc4": [
      7,
      11,
      12
    ],
    "5ed74f09": [
      7,
      11,
      12
    ],
    "169c3fa4": [
      7,
      11,
      12
    ],
    "1448b12e": [
      9
    ],
    "3cb8fe26": [
      9
    ],
    "2baf8943": [
      9
    ],
    "7aa14476": [
      9
    ],
    "296a30ea": [
      9
    ],
    "c652e246": [
      9
    ],
    "4f6bfc93": [
      9
    ],
    "a4148fda": [
      9
    ],
    "e45f4b8a": [
      9
    ],
    "09844ec7": [
      9
    ],
    "74ddaf47": [
      9
    ],
    "ce2358ce": [
      9
    ],
    "16bdffce": [
      9
    ],
    "43c1d48f": [
      4,
      17
    ],
    "78a02a9a": [
      7,
      11,
      12
    ],
    "ac55aa0e": [
      9
    ],
    "76ca9358": [
      9
    ],
    "063d62f6": [
      9
    ],
    "00acd2c8": [
      9
    ],
    "237d28b0": [
      9
    ],
    "5be11c76": [
      9
    ],
    "6e5d244f": [
      9
    ],
    "35cb9245": [
      9
    ],
    "64065e26": [
      9
    ],
    "3dd24292": [
      9
    ],
    "f11ef834": [
      9
    ],
    "af4cbf22": [
      9
    ],
    "1ce8b07a": [
      9
    ],
    "7fa6262d": [
      9
    ],
    "7b1d4cde": [
      9
    ],
    "2feaba0c": [
      9
    ],
    "33b360f2": [
      9
    ],
    "4f49359e": [
      9
    ],
    "5de7dc8a": [
      9
    ],
    "7d1dd76c": [
      9
    ],
    "64d60e90": [
      9
    ],
    "4c3e73a9": [
      9
    ],
    "ff21e452": [
      9
    ],
    "6ade5ec6": [
      9
    ],
    "eef2aa68": [
      9
    ],
    "35cbfacd": [
      7,
      11,
      12
    ],
    "1eb257cc": [
      7,
      11,
      12
    ],
    "5c7ae3b8": [
      7,
      11,
      12
    ],
    "3e93494e": [
      7,
      11,
      12
    ],
    "49290e76": [
      7,
      11,
      12
    ],
    "456b1e38": [
      7,
      11,
      12
    ],
    "e24bf88a": [
      7,
      11,
      12
    ],
    "3919428b": [
      9
    ],
    "52444e9b": [
      9
    ],
    "2d85b8ba": [
      9
    ],
    "41bc1604": [
      9
    ],
    "2005b29c": [
      9
    ],
    "3f55755c": [
      9
    ],
    "06fc6634": [
      9
    ],
    "e59596bc": [
      9
    ],
    "a4191b90": [
      9
    ],
    "6ec7d83a": [
      7,
      11,
      12
    ],
    "4773e6b8": [
      7,
      11,
      12
    ],
    "3202fd44": [
      9
    ],
    "1f182f4e": [
      9
    ],
    "db3610be": [
      7,
      11,
      12
    ],
    "32d5c478": [
      7,
      11,
      12
    ],
    "9c4c741e": [
      4,
      17
    ],
    "78560ee6": [
      9
    ],
    "3e6079ae": [
      9
    ],
    "5ede2a6b": [
      9
    ],
    "2de10e53": [
      9
    ],
    "2592380c": [
      9
    ],
    "ba118fd0": [
      9
    ],
    "23d5ca02": [
      9
    ],
    "254fa623": [
      9
    ],
    "8420a18c": [
      7,
      11,
      12
    ],
    "cf6dbe74": [
      4,
      17
    ],
    "e2912e94": [
      4,
      17
    ],
    "4a71e740": [
      9
    ],
    "1cf83880": [
      9
    ],
    "b810f69c": [
      9
    ],
    "62bf5595": [
      9
    ],
    "3e7a1890": [
      9
    ],
    "4b6be859": [
      9
    ],
    "d920e462": [
      9
    ],
    "67dc0df6": [
      9
    ],
    "0643674a": [
      9
    ],
    "8e23ff46": [
      9
    ],
    "7b83493a": [
      9
    ],
    "cc496d10": [
      9
    ],
    "7265bbd4": [
      9
    ],
    "c88047d2": [
      9
    ],
    "167ade3f": [
      9
    ],
    "0504f6aa": [
      9
    ],
    "7441e835": [
      9
    ],
    "37209a23": [
      9
    ],
    "4ad8d122": [
      9
    ],
    "141dcbda": [
      9
    ],
    "556e8176": [
      9
    ],
    "5e594a5b": [
      9
    ],
    "2137fc49": [
      9
    ],
    "aecde974": [
      9
    ],
    "6263fdba": [
      9
    ],
    "374043b4": [
      9
    ],
    "29c5b884": [
      9
    ],
    "e4b68368": [
      9
    ],
    "8059aa44": [
      9
    ],
    "da9f23b6": [
      9
    ],
    "f66559d2": [
      4,
      17
    ],
    "c202d57a": [
      4,
      17
    ],
    "107a4eba": [
      4,
      17
    ],
    "4aac3fcf": [
      4,
      17
    ],
    "44b09b46": [
      7,
      11,
      12
    ],
    "7750ec1c": [
      7,
      11,
      12
    ],
    "4ca5d4fc": [
      7,
      11,
      12
    ],
    "b0bb93fc": [
      7,
      11,
      12
    ],
    "f9691798": [
      4,
      17
    ],
    "db821d96": [
      4,
      17
    ],
    "02ce48ee": [
      4,
      17
    ],
    "a03ef8d6": [
      4,
      17
    ],
    "1cbab07e": [
      4,
      17
    ],
    "dfb92a5c": [
      7,
      11,
      12
    ],
    "66fba177": [
      7,
      11,
      12
    ],
    "535df24a": [
      7,
      11,
      12
    ],
    "7c28616e": [
      7,
      11,
      12
    ],
    "78fc43ac": [
      7,
      11,
      12
    ],
    "531780e2": [
      7,
      11,
      12
    ],
    "b66e0db2": [
      7,
      11,
      12
    ],
    "c78b963c": [
      7,
      11,
      12
    ],
    "1a5046a2": [
      7,
      11,
      12
    ],
    "01acafb2": [
      7,
      11,
      12
    ],
    "9e854516": [
      7,
      11,
      12
    ],
    "79f408f8": [
      7,
      11,
      12
    ],
    "1b01c4ed": [
      7,
      11,
      12
    ],
    "4575d7cc": [
      7,
      11,
      12
    ],
    "ad741884": [
      7,
      11,
      12
    ],
    "3dd09f1d": [
      7,
      11,
      12
    ],
    "12176d04": [
      7,
      11,
      12
    ],
    "fa1a01e2": [
      7,
      11,
      12
    ],
    "10cf7094": [
      7,
      11,
      12
    ],
    "2da9432a": [
      7,
      11,
      12
    ],
    "7b2c2db8": [
      7,
      11,
      12
    ],
    "1e3fb187": [
      7,
      11,
      12
    ],
    "a9feafb2": [
      7,
      11,
      12
    ],
    "4fe11dc6": [
      9
    ],
    "558ab1ee": [
      9
    ],
    "1f686a36": [
      9
    ],
    "c612ecc4": [
      9
    ],
    "83cf2862": [
      9
    ],
    "005c0443": [
      9
    ],
    "3ed96598": [
      9
    ],
    "6216a05e": [
      9
    ],
    "cd4c158c": [
      7,
      11,
      12
    ],
    "13fc90d7": [
      9
    ],
    "324cf8bc": [
      9
    ],
    "a6122646": [
      9
    ],
    "a1704b0a": [
      9
    ],
    "2194c369": [
      9
    ],
    "212d0497": [
      9
    ],
    "26b17bca": [
      9
    ],
    "26e80556": [
      9
    ],
    "e897d738": [
      9
    ],
    "505868ce": [
      9
    ],
    "7a9ebaaa": [
      9
    ],
    "f7b9d812": [
      7,
      11,
      12
    ],
    "2d469497": [
      9
    ],
    "2b14e30f": [
      9
    ],
    "10711ffd": [
      9
    ],
    "73c12928": [
      9
    ],
    "36360aec": [
      9
    ],
    "ede5eb38": [
      9
    ],
    "a42232fc": [
      9
    ],
    "7091b773": [
      9
    ],
    "035334de": [
      9
    ],
    "6a52c6ed": [
      9
    ],
    "5c45fded": [
      7,
      11,
      12
    ],
    "52a2b878": [
      7,
      11,
      12
    ],
    "3a4d05d0": [
      7,
      11,
      12
    ],
    "6884673c": [
      7,
      11,
      12
    ],
    "07c1ea98": [
      7,
      11,
      12
    ],
    "785d063f": [
      7,
      11,
      12
    ],
    "57ab338e": [
      7,
      11,
      12
    ],
    "8fa43da8": [
      7,
      11,
      12
    ],
    "def40348": [
      7,
      11,
      12
    ],
    "25cdfaf4": [
      7,
      11,
      12
    ],
    "f25a66ae": [
      7,
      11,
      12
    ],
    "7cde3598": [
      7,
      11,
      12
    ],
    "394e97d3": [
      7,
      11,
      12
    ],
    "2d0faf16": [
      7,
      11,
      12
    ],
    "24987b58": [
      7,
      11,
      12
    ],
    "6aaca73e": [
      7,
      11,
      12
    ],
    "84c37088": [
      7,
      11,
      12
    ],
    "76a03441": [
      7,
      11,
      12
    ],
    "727751ef": [
      7,
      11,
      12
    ],
    "52c9bd44": [
      7,
      11,
      12
    ],
    "2cd2123a": [
      7,
      11,
      12
    ],
    "6f016f3b": [
      7,
      11,
      12
    ],
    "459f723c": [
      7,
      11,
      12
    ],
    "5e279678": [
      7,
      11,
      12
    ],
    "5ef90332": [
      7,
      11,
      12
    ],
    "775f02f0": [
      7,
      11,
      12
    ],
    "b6ea6180": [
      7,
      11,
      12
    ],
    "55ce4e3d": [
      7,
      11,
      12
    ],
    "6b68c4a2": [
      3
    ],
    "1217eaf0": [
      3
    ],
    "5c37c16e": [
      3
    ],
    "30ab0c96": [
      3
    ],
    "517cbd3c": [
      3
    ],
    "1732522d": [
      3
    ],
    "eb38776a": [
      3
    ],
    "36f77eb9": [
      3
    ],
    "1a4fbee6": [
      3
    ],
    "dcdddaa6": [
      3
    ],
    "4f76a61c": [
      3
    ],
    "5071f5c6": [
      3
    ],
    "657eee98": [
      3
    ],
    "9e208bc6": [
      3
    ],
    "65dc91b2": [
      3
    ],
    "5045adca": [
      3
    ],
    "a8a28db4": [
      3
    ],
    "d7b820e0": [
      3
    ],
    "95626bd6": [
      3
    ],
    "19da9cb8": [
      3
    ],
    "45d18db0": [
      3
    ],
    "2deffe44": [
      3
    ],
    "e627bff2": [
      3
    ],
    "57dc1980": [
      3
    ],
    "0b9a47bd": [
      3
    ],
    "4a3536df": [
      3
    ],
    "36702a24": [
      3
    ],
    "6dfa156c": [
      3
    ],
    "7e5e9e26": [
      3
    ],
    "4bd85b1c": [
      3
    ],
    "4cc71fef": [
      3
    ],
    "37300a10": [
      3
    ],
    "49c78225": [
      3
    ],
    "3c94f1dc": [
      3
    ],
    "5bb4c569": [
      3
    ],
    "4ad9df78": [
      3
    ],
    "379bc448": [
      3
    ],
    "3d01222e": [
      3
    ],
    "0dbb766c": [
      3
    ],
    "d49f109e": [
      3
    ],
    "3e1a5fa7": [
      3
    ],
    "47e6db95": [
      3
    ],
    "962bcdb2": [
      3
    ],
    "53310aff": [
      3
    ],
    "29abc3e5": [
      3
    ],
    "0248c3c5": [
      3
    ],
    "4f0710c2": [
      3
    ],
    "b08623aa": [
      3
    ],
    "ca34118a": [
      3
    ],
    "20b16109": [
      3
    ],
    "c4178e1c": [
      3
    ],
    "470b1d91": [
      3
    ],
    "c5911502": [
      3
    ],
    "7d9be601": [
      3
    ],
    "f96c0102": [
      3
    ],
    "2cd68abe": [
      3
    ],
    "249acdf6": [
      3
    ],
    "6dd45124": [
      3
    ],
    "3ab22873": [
      3
    ],
    "3930fa4c": [
      3
    ],
    "600dc38e": [
      3
    ],
    "3259b7aa": [
      3
    ],
    "5ecda488": [
      3
    ],
    "06a52a42": [
      3
    ],
    "05d2d588": [
      3
    ],
    "5056fc4d": [
      3
    ],
    "d594aed2": [
      3
    ],
    "3a923af6": [
      3
    ],
    "14a05672": [
      3
    ],
    "261e48c6": [
      3
    ],
    "bf6180e4": [
      3
    ],
    "6bf1bf30": [
      3
    ],
    "6d1d34af": [
      3
    ],
    "cd1f545a": [
      3
    ],
    "26365fb1": [
      3
    ],
    "0f84dfc9": [
      3
    ],
    "6cdcb1c2": [
      3
    ],
    "577267f1": [
      3
    ],
    "831ad376": [
      3
    ],
    "4d552b54": [
      3
    ],
    "31636ac5": [
      3
    ],
    "1daa86fe": [
      3
    ],
    "9388c136": [
      3
    ],
    "fc6da48a": [
      3
    ],
    "2a25e2ef": [
      3
    ],
    "56994f4b": [
      3
    ],
    "349d2629": [
      3
    ],
    "8f8a93a2": [
      3
    ],
    "aad6557e": [
      3
    ],
    "c5bb858a": [
      3
    ],
    "0240a4d6": [
      3
    ],
    "7f25aab7": [
      3
    ],
    "3babf51c": [
      3
    ],
    "5723e822": [
      3
    ],
    "1925806b": [
      3
    ],
    "1770a7cc": [
      3
    ],
    "34730a5b": [
      3
    ],
    "e221743c": [
      3
    ],
    "23e0a798": [
      3
    ],
    "579fd984": [
      3
    ],
    "d5597f72": [
      3
    ],
    "45a87b48": [
      3
    ],
    "aefb8baa": [
      3
    ],
    "0a69e1e5": [
      3
    ],
    "7cb93520": [
      3
    ],
    "3e728ea6": [
      3
    ],
    "6298a28e": [
      3
    ],
    "5a71a01f": [
      3
    ],
    "d5fd5fbe": [
      3
    ],
    "69780c95": [
      3
    ],
    "4eddb5a5": [
      3
    ],
    "23619cd2": [
      3
    ],
    "191d18c1": [
      3
    ],
    "54e4ea1b": [
      3
    ],
    "8a72624c": [
      3
    ],
    "61b29063": [
      3
    ],
    "327bf821": [
      3
    ],
    "040b221e": [
      3
    ],
    "c2639b2c": [
      3
    ],
    "49bae38a": [
      3
    ],
    "0c87696b": [
      3
    ],
    "26ac48bc": [
      3
    ],
    "2e35d6a2": [
      3
    ],
    "a142e192": [
      3
    ],
    "64f11c8c": [
      3
    ],
    "4d9d54e6": [
      3
    ],
    "6e9dea4b": [
      3
    ],
    "3247317a": [
      3
    ],
    "e97da97e": [
      3
    ],
    "7a0a006b": [
      3
    ],
    "d3f5fafc": [
      3
    ],
    "fe36ae52": [
      3
    ],
    "19bbb4e0": [
      3
    ],
    "1a80fdee": [
      3
    ],
    "107ccfe4": [
      3
    ],
    "16add216": [
      3
    ],
    "2d62af08": [
      3
    ],
    "e9dc6044": [
      3
    ],
    "3674df20": [
      3
    ],
    "f8ed1824": [
      3
    ],
    "58952a04": [
      3
    ],
    "5d54b09e": [
      3
    ],
    "0f9b5dca": [
      3
    ],
    "3de2e9f8": [
      3
    ],
    "5201273a": [
      3
    ],
    "4aa5d21b": [
      3
    ],
    "4e8439dc": [
      3
    ],
    "c716b672": [
      3
    ],
    "64977ed2": [
      3
    ],
    "52e95216": [
      3
    ],
    "4cf3a1d8": [
      3
    ],
    "c52016b8": [
      3
    ],
    "1fa64dfe": [
      3
    ],
    "00123560": [
      3
    ],
    "54b4dc61": [
      3
    ],
    "42009b49": [
      3
    ],
    "4322db08": [
      3
    ],
    "3a7b5834": [
      3
    ],
    "b1a4519e": [
      3
    ],
    "a6778fbc": [
      3
    ],
    "0845cb28": [
      3
    ],
    "4a94a295": [
      3
    ],
    "ad86197a": [
      3
    ],
    "76bd394a": [
      3
    ],
    "507378b6": [
      3
    ],
    "856ab4b6": [
      3
    ],
    "08733687": [
      3
    ],
    "202f1cac": [
      3
    ],
    "8366d360": [
      3
    ],
    "4632fca2": [
      3
    ],
    "59b8cbb0": [
      3
    ],
    "37e56bc2": [
      3
    ],
    "590699aa": [
      3
    ],
    "69a473c6": [
      3
    ],
    "aec6b210": [
      3
    ],
    "feec1fd8": [
      3
    ],
    "47c57bc0": [
      3
    ],
    "5583dad8": [
      3
    ],
    "083a8d98": [
      3
    ],
    "6fb3cac2": [
      3
    ],
    "9c5094c0": [
      3
    ],
    "4b37f8e0": [
      3
    ],
    "6920607f": [
      3
    ],
    "aee71a88": [
      3
    ],
    "aff6e746": [
      3
    ],
    "6db99863": [
      3
    ],
    "96f86b46": [
      3
    ],
    "024b0c6d": [
      3
    ],
    "1b037289": [
      3
    ],
    "168c2719": [
      3
    ],
    "53fbf09e": [
      3
    ],
    "74314c73": [
      3
    ],
    "2d54fd64": [
      3
    ],
    "8c6cb3a2": [
      3
    ],
    "15ef34e4": [
      3
    ],
    "f17aae36": [
      3
    ],
    "2ac6c98c": [
      3
    ],
    "66fe8653": [
      3
    ],
    "dc2cabfe": [
      3
    ],
    "09a14dc4": [
      3
    ],
    "e0f63748": [
      3
    ],
    "5948dd7d": [
      3
    ],
    "1d8c835c": [
      3
    ],
    "23ea6b0e": [
      3
    ],
    "608cb903": [
      3
    ],
    "704c2b14": [
      3
    ],
    "4f9c9648": [
      3
    ],
    "7d5bfcee": [
      3
    ],
    "1d21f4e9": [
      3
    ],
    "36e8efcc": [
      3
    ],
    "d264d11e": [
      3
    ],
    "398fc0e6": [
      3
    ],
    "5f8a6468": [
      3
    ],
    "2a632d42": [
      3
    ],
    "4840b49c": [
      3
    ],
    "a30e520a": [
      3
    ],
    "a9495694": [
      3
    ],
    "0eb7b584": [
      3
    ],
    "73608fa2": [
      3
    ],
    "0abcc048": [
      3
    ],
    "4584c6fa": [
      3
    ],
    "052ade80": [
      3
    ],
    "1e4e1fa6": [
      3
    ],
    "91fa1154": [
      3
    ],
    "4cde6e76": [
      3
    ],
    "0fa93c59": [
      3
    ],
    "2d943e22": [
      3
    ],
    "470a96ea": [
      3
    ],
    "3be29e26": [
      3
    ],
    "ee17d66e": [
      3
    ],
    "369f3964": [
      3
    ],
    "0389a5ad": [
      3
    ],
    "c1d8d4b4": [
      3
    ],
    "6024f0c7": [
      3
    ],
    "28b996bc": [
      3
    ],
    "fef46baa": [
      3
    ],
    "08f6e1d0": [
      3
    ],
    "d26d2ca6": [
      3
    ],
    "17358e88": [
      3
    ],
    "9843b388": [
      3
    ],
    "646fd8f0": [
      3
    ],
    "1b34433a": [
      3
    ],
    "27cfac4d": [
      3
    ],
    "163c4a00": [
      3
    ],
    "37b36ac0": [
      3
    ],
    "6c01e691": [
      3
    ],
    "aeb509b4": [
      3
    ],
    "1dc1c270": [
      3
    ],
    "1c5c7749": [
      3
    ],
    "c9894b8e": [
      3
    ],
    "10a733b9": [
      3
    ],
    "0404fa6c": [
      3
    ],
    "04056ecb": [
      3
    ],
    "c7cac6ec": [
      3
    ],
    "2709a1af": [
      3
    ],
    "5d2b2f36": [
      3
    ],
    "00dc7a54": [
      3
    ],
    "432cc950": [
      3
    ],
    "c0e25e26": [
      3
    ],
    "678b93ec": [
      3
    ],
    "3388a790": [
      3
    ],
    "10c51d63": [
      3
    ],
    "6b02d178": [
      3
    ],
    "f46c4c60": [
      3
    ],
    "5b226c7e": [
      3
    ],
    "26a53042": [
      3
    ],
    "315018be": [
      3
    ],
    "07ef134c": [
      3
    ],
    "cfaeb590": [
      3
    ],
    "554dbef2": [
      3
    ],
    "574ccee4": [
      3
    ],
    "7e7b28b0": [
      3
    ],
    "170d0944": [
      3
    ],
    "23b1e398": [
      3
    ],
    "6f6053a3": [
      3
    ],
    "6b3b06d2": [
      3
    ],
    "d8e7f2d8": [
      3
    ],
    "20000db4": [
      3
    ],
    "061c9a48": [
      3
    ],
    "bdae0846": [
      3
    ],
    "7fb7741e": [
      3
    ],
    "af59276c": [
      3
    ],
    "4cf6751a": [
      3
    ],
    "74ad2f7a": [
      3
    ],
    "8645f2ca": [
      3
    ],
    "32f3c910": [
      3
    ],
    "54640e9c": [
      3
    ],
    "004e210a": [
      3
    ],
    "2178e6ca": [
      3
    ],
    "8caa25f6": [
      3
    ],
    "68cea252": [
      3
    ],
    "00a6e004": [
      3
    ],
    "1c99ac36": [
      8,
      18,
      16,
      14,
      13,
      15
    ],
    "b4d359e6": [
      3
    ],
    "731d9e42": [
      8,
      18,
      16,
      14,
      13,
      15
    ],
    "7861a77c": [
      8,
      18,
      16,
      14,
      13,
      15
    ],
    "7b4bbf64": [
      8,
      18,
      16,
      14,
      13,
      15
    ],
    "b2042d5c": [
      8,
      18,
      16,
      14,
      13,
      15
    ],
    "58d49d32": [
      8,
      18,
      16,
      14,
      13,
      15
    ],
    "2d03cbe5": [
      8,
      18,
      16,
      14,
      13,
      15
    ],
    "69e377fc": [
      8,
      18,
      16,
      14,
      13,
      15
    ],
    "2b4217aa": [
      8,
      18,
      16,
      14,
      13,
      15
    ],
    "61e95789": [
      8,
      18,
      16,
      14,
      13,
      15
    ],
    "61763e47": [
      8,
      18,
      16,
      14,
      13,
      15
    ],
    "9152f38a": [
      8,
      18,
      16,
      14,
      13,
      15
    ],
    "0dc2271c": [
      8,
      18,
      16,
      14,
      13,
      15
    ],
    "495b0bd3": [
      8,
      18,
      16,
      14,
      13,
      15
    ],
    "a9fb5caa": [
      8,
      18,
      16,
      14,
      13,
      15
    ],
    "307032ac": [
      8,
      18,
      16,
      14,
      13,
      15
    ],
    "2005378a": [
      8,
      18,
      16,
      14,
      13,
      15
    ],
    "3f1b7814": [
      8,
      18,
      16,
      14,
      13,
      15
    ],
    "0cc8c2a4": [
      8,
      18,
      16,
      14,
      13,
      15
    ],
    "3b0ccdce": [
      8,
      18,
      16,
      14,
      13,
      15
    ],
    "3827cccc": [
      8,
      18,
      16,
      14,
      13,
      15
    ],
    "2dbe2b44": [
      8,
      18,
      16,
      14,
      13,
      15
    ],
    "75f40594": [
      8,
      18,
      16,
      14,
      13,
      15
    ],
    "51837e50": [
      8,
      18,
      16,
      14,
      13,
      15
    ],
    "01e1deec": [
      8,
      18,
      16,
      14,
      13,
      15
    ],
    "17240eb6": [
      8,
      18,
      16,
      14,
      13,
      15
    ],
    "a583f0d2": [
      3
    ],
    "158a902a": [
      3
    ],
    "6def8af3": [
      8,
      18,
      16,
      14,
      13,
      15
    ],
    "006bdf81": [
      8,
      18,
      16,
      14,
      13,
      15
    ],
    "6b58bcde": [
      8,
      18,
      16,
      14,
      13,
      15
    ],
    "ca8589f2": [
      8,
      18,
      16,
      14,
      13,
      15
    ],
    "4353e569": [
      8,
      18,
      16,
      14,
      13,
      15
    ],
    "082228a6": [
      8,
      18,
      16,
      14,
      13,
      15
    ],
    "1a533ca4": [
      8,
      18,
      16,
      14,
      13,
      15
    ],
    "0c41b956": [
      8,
      18,
      16,
      14,
      13,
      15
    ],
    "0b3d0bb4": [
      8,
      18,
      16,
      14,
      13,
      15
    ],
    "66ff9702": [
      8,
      18,
      16,
      14,
      13,
      15
    ],
    "1b3ee090": [
      8,
      18,
      16,
      14,
      13,
      15
    ],
    "a6bc6002": [
      8,
      18,
      16,
      14,
      13,
      15
    ],
    "7cbe0e4f": [
      8,
      18,
      16,
      14,
      13,
      15
    ],
    "5c0c7fa7": [
      8,
      18,
      16,
      14,
      13,
      15
    ],
    "493da541": [
      8,
      18,
      16,
      14,
      13,
      15
    ],
    "764cf39e": [
      8,
      18,
      16,
      14,
      13,
      15
    ],
    "a09ffc96": [
      8,
      18,
      16,
      14,
      13,
      15
    ],
    "5698a836": [
      8,
      18,
      16,
      14,
      13,
      15
    ],
    "63b812c5": [
      8,
      18,
      16,
      14,
      13,
      15
    ],
    "4bcb4c4e": [
      8,
      18,
      16,
      14,
      13,
      15
    ],
    "464db3a4": [
      8,
      18,
      16,
      14,
      13,
      15
    ],
    "e83a5d18": [
      8,
      18,
      16,
      14,
      13,
      15
    ],
    "2467961c": [
      8,
      18,
      16,
      14,
      13,
      15
    ],
    "6fae8def": [
      8,
      18,
      16,
      14,
      13,
      15
    ],
    "3967c77e": [
      8,
      18,
      16,
      14,
      13,
      15
    ],
    "602775e3": [
      8,
      18,
      16,
      14,
      13,
      15
    ],
    "b309da50": [
      8,
      18,
      16,
      14,
      13,
      15
    ],
    "b56a2a42": [
      8,
      18,
      16,
      14,
      13,
      15
    ],
    "503c588e": [
      8,
      18,
      16,
      14,
      13,
      15
    ],
    "2dae1290": [
      8,
      18,
      16,
      14,
      13,
      15
    ],
    "28fa90a0": [
      8,
      18,
      16,
      14,
      13,
      15
    ],
    "3eab3592": [
      8,
      18,
      16,
      14,
      13,
      15
    ],
    "e8445dbc": [
      8,
      18,
      16,
      14,
      13,
      15
    ],
    "fbf559b0": [
      8,
      18,
      16,
      14,
      13,
      15
    ],
    "2032a536": [
      8,
      18,
      16,
      14,
      13,
      15
    ],
    "4560ace9": [
      8,
      18,
      16,
      14,
      13,
      15
    ],
    "32e5a0a7": [
      8,
      18,
      16,
      14,
      13,
      15
    ],
    "f07debe8": [
      8,
      18,
      16,
      14,
      13,
      15
    ],
    "4db312bf": [
      8,
      18,
      16,
      14,
      13,
      15
    ],
    "7a180d80": [
      8,
      18,
      16,
      14,
      13,
      15
    ],
    "6266f7c3": [
      8,
      18,
      16,
      14,
      13,
      15
    ],
    "1e8fd7f1": [
      8,
      18,
      16,
      14,
      13,
      15
    ],
    "6b1ffb28": [
      8,
      18,
      16,
      14,
      13,
      15
    ],
    "17e54d16": [
      8,
      18,
      16,
      14,
      13,
      15
    ],
    "84ef471e": [
      8,
      18,
      16,
      14,
      13,
      15
    ],
    "b91aaa2a": [
      8,
      18,
      16,
      14,
      13,
      15
    ],
    "59b4cd01": [
      8,
      18,
      16,
      14,
      13,
      15
    ],
    "581cf62d": [
      8,
      18,
      16,
      14,
      13,
      15
    ],
    "a2cac53e": [
      8,
      18,
      16,
      14,
      13,
      15
    ],
    "d0ae8e32": [
      8,
      18,
      16,
      14,
      13,
      15
    ],
    "1b022d2b": [
      8,
      18,
      16,
      14,
      13,
      15
    ],
    "56a2d86b": [
      8,
      18,
      16,
      14,
      13,
      15
    ],
    "37a40b0a": [
      8,
      18,
      16,
      14,
      13,
      15
    ],
    "89d1c016": [
      8,
      18,
      16,
      14,
      13,
      15
    ],
    "83bf43c6": [
      8,
      18,
      16,
      14,
      13,
      15
    ],
    "da791400": [
      8,
      18,
      16,
      14,
      13,
      15
    ],
    "3f9c4665": [
      8,
      18,
      16,
      14,
      13,
      15
    ],
    "6d86c734": [
      8,
      18,
      16,
      14,
      13,
      15
    ],
    "458c9796": [
      8,
      18,
      16,
      14,
      13,
      15
    ],
    "fa1bdcf0": [
      8,
      18,
      16,
      14,
      13,
      15
    ],
    "c06156d0": [
      8,
      18,
      16,
      14,
      13,
      15
    ],
    "28a1d2fa": [
      8,
      18,
      16,
      14,
      13,
      15
    ],
    "04176162": [
      8,
      18,
      16,
      14,
      13,
      15
    ],
    "33cd3f44": [
      8,
      18,
      16,
      14,
      13,
      15
    ],
    "711a89ba": [
      8,
      18,
      16,
      14,
      13,
      15
    ],
    "0e674862": [
      8,
      18,
      16,
      14,
      13,
      15
    ],
    "c71166dc": [
      8,
      18,
      16,
      14,
      13,
      15
    ],
    "2e9a71e6": [
      8,
      18,
      16,
      14,
      13,
      15
    ],
    "0afa3a62": [
      8,
      18,
      16,
      14,
      13,
      15
    ],
    "496f4be7": [
      8,
      18,
      16,
      14,
      13,
      15
    ],
    "01aa0cca": [
      8,
      18,
      16,
      14,
      13,
      15
    ],
    "403986ab": [
      8,
      18,
      16,
      14,
      13,
      15
    ],
    "70f70850": [
      8,
      18,
      16,
      14,
      13,
      15
    ],
    "9125c9a2": [
      8,
      18,
      16,
      14,
      13,
      15
    ],
    "8d76d4ce": [
      8,
      18,
      16,
      14,
      13,
      15
    ],
    "534cc025": [
      8,
      18,
      16,
      14,
      13,
      15
    ],
    "00bd0429": [
      8,
      18,
      16,
      14,
      13,
      15
    ],
    "1b7cb7e7": [
      8,
      18,
      16,
      14,
      13,
      15
    ],
    "ab5252ee": [
      8,
      18,
      16,
      14,
      13,
      15
    ],
    "a0f18426": [
      8,
      18,
      16,
      14,
      13,
      15
    ],
    "9b1cf1fa": [
      8,
      18,
      16,
      14,
      13,
      15
    ],
    "8c67c942": [
      8,
      18,
      16,
      14,
      13,
      15
    ],
    "3a94f425": [
      8,
      18,
      16,
      14,
      13,
      15
    ],
    "07e700fe": [
      8,
      18,
      16,
      14,
      13,
      15
    ],
    "4cb0727a": [
      8,
      18,
      16,
      14,
      13,
      15
    ],
    "5facbb66": [
      8,
      18,
      16,
      14,
      13,
      15
    ],
    "b28c5796": [
      8,
      18,
      16,
      14,
      13,
      15
    ],
    "d34a07e6": [
      8,
      18,
      16,
      14,
      13,
      15
    ],
    "172f6fea": [
      8,
      18,
      16,
      14,
      13,
      15
    ],
    "411499ed": [
      8,
      18,
      16,
      14,
      13,
      15
    ],
    "d984fec0": [
      8,
      18,
      16,
      14,
      13,
      15
    ],
    "450bb030": [
      8,
      18,
      16,
      14,
      13,
      15
    ],
    "43559eb1": [
      8,
      18,
      16,
      14,
      13,
      15
    ],
    "30ac5793": [
      8,
      18,
      16,
      14,
      13,
      15
    ],
    "dfa0987c": [
      8,
      18,
      16,
      14,
      13,
      15
    ],
    "1e22a1b2": [
      8,
      18,
      16,
      14,
      13,
      15
    ],
    "3a45b7c8": [
      8,
      18,
      16,
      14,
      13,
      15
    ],
    "1634752c": [
      8,
      18,
      16,
      14,
      13,
      15
    ],
    "2b44544e": [
      8,
      18,
      16,
      14,
      13,
      15
    ],
    "06571c73": [
      8,
      18,
      16,
      14,
      13,
      15
    ],
    "e348a6c2": [
      8,
      18,
      16,
      14,
      13,
      15
    ],
    "299cae7a": [
      8,
      18,
      16,
      14,
      13,
      15
    ],
    "0b8dd247": [
      8,
      18,
      16,
      14,
      13,
      15
    ],
    "e4807e9a": [
      8,
      18,
      16,
      14,
      13,
      15
    ],
    "2cb7e09a": [
      8,
      18,
      16,
      14,
      13,
      15
    ],
    "0005bbee": [
      8,
      18,
      16,
      14,
      13,
      15
    ],
    "4942e7e8": [
      8,
      18,
      16,
      14,
      13,
      15
    ],
    "e6b5ff90": [
      8,
      18,
      16,
      14,
      13,
      15
    ],
    "7dd4acfc": [
      3
    ],
    "a455ade6": [
      3
    ],
    "cac65d2a": [
      3
    ],
    "6ee2f0ec": [
      8,
      18,
      16,
      14,
      13,
      15
    ],
    "468327de": [
      8,
      18,
      16,
      14,
      13,
      15
    ],
    "72646c3d": [
      8,
      18,
      16,
      14,
      13,
      15
    ],
    "2fed1191": [
      8,
      18,
      16,
      14,
      13,
      15
    ],
    "931345c4": [
      8,
      18,
      16,
      14,
      13,
      15
    ],
    "4cc53b58": [
      8,
      18,
      16,
      14,
      13,
      15
    ],
    "579202a8": [
      8,
      18,
      16,
      14,
      13,
      15
    ],
    "7cc88abc": [
      8,
      18,
      16,
      14,
      13,
      15
    ],
    "9a750f5c": [
      8,
      18,
      16,
      14,
      13,
      15
    ],
    "19363b04": [
      8,
      18,
      16,
      14,
      13,
      15
    ],
    "175e8bcd": [
      8,
      18,
      16,
      14,
      13,
      15
    ],
    "2d268f9e": [
      8,
      18,
      16,
      14,
      13,
      15
    ],
    "2a0c225d": [
      8,
      18,
      16,
      14,
      13,
      15
    ],
    "03bd069f": [
      8,
      18,
      16,
      14,
      13,
      15
    ],
    "7b4517f3": [
      8,
      18,
      16,
      14,
      13,
      15
    ],
    "4a342f8d": [
      8,
      18,
      16,
      14,
      13,
      15
    ],
    "8a73aa3a": [
      8,
      18,
      16,
      14,
      13,
      15
    ],
    "441bb30f": [
      8,
      18,
      16,
      14,
      13,
      15
    ],
    "a0c3a308": [
      8,
      18,
      16,
      14,
      13,
      15
    ],
    "1131cbc4": [
      8,
      18,
      16,
      14,
      13,
      15
    ],
    "caf15820": [
      8,
      18,
      16,
      14,
      13,
      15
    ],
    "4e956e96": [
      8,
      18,
      16,
      14,
      13,
      15
    ],
    "a6df9baa": [
      8,
      18,
      16,
      14,
      13,
      15
    ],
    "0392f47f": [
      8,
      18,
      16,
      14,
      13,
      15
    ],
    "5bc60708": [
      8,
      18,
      16,
      14,
      13,
      15
    ],
    "557fbf98": [
      8,
      18,
      16,
      14,
      13,
      15
    ],
    "c3d7abf6": [
      8,
      18,
      16,
      14,
      13,
      15
    ],
    "db77a6da": [
      8,
      18,
      16,
      14,
      13,
      15
    ],
    "09cc3de7": [
      8,
      18,
      16,
      14,
      13,
      15
    ],
    "ef91fccc": [
      8,
      18,
      16,
      14,
      13,
      15
    ],
    "d6bfcac4": [
      8,
      18,
      16,
      14,
      13,
      15
    ],
    "2b0da9ca": [
      8,
      18,
      16,
      14,
      13,
      15
    ],
    "ea4fd0cc": [
      3
    ],
    "67531ab0": [
      3
    ],
    "9949f568": [
      8,
      18,
      16,
      14,
      13,
      15
    ],
    "2cd51e78": [
      8,
      18,
      16,
      14,
      13,
      15
    ],
    "7adfa314": [
      8,
      18,
      16,
      14,
      13,
      15
    ],
    "032f98a2": [
      8,
      18,
      16,
      14,
      13,
      15
    ],
    "929f457e": [
      3
    ],
    "99fa566a": [
      3
    ],
    "428be118": [
      8,
      18,
      16,
      14,
      13,
      15
    ],
    "583428a0": [
      8,
      18,
      16,
      14,
      13,
      15
    ],
    "3638388b": [
      3
    ],
    "731ecb9c": [
      8,
      18,
      16,
      14,
      13,
      15
    ],
    "30a770f0": [
      8,
      18,
      16,
      14,
      13,
      15
    ],
    "4b63f1de": [
      8,
      18,
      16,
      14,
      13,
      15
    ],
    "6a47520a": [
      8,
      18,
      16,
      14,
      13,
      15
    ],
    "8f922e10": [
      8,
      18,
      16,
      14,
      13,
      15
    ],
    "a87a23b8": [
      8,
      18,
      16,
      14,
      13,
      15
    ],
    "446fb0e2": [
      8,
      18,
      16,
      14,
      13,
      15
    ],
    "01f85636": [
      8,
      18,
      16,
      14,
      13,
      15
    ],
    "f2440de4": [
      8,
      18,
      16,
      14,
      13,
      15
    ],
    "04d29962": [
      8,
      18,
      16,
      14,
      13,
      15
    ],
    "089faccc": [
      8,
      18,
      16,
      14,
      13,
      15
    ],
    "4522eb46": [
      2
    ],
    "401bf7f8": [
      2
    ],
    "5fb592ee": [
      2
    ],
    "1bd3e732": [
      2
    ],
    "24cb15b1": [
      2
    ],
    "05b335bc": [
      6
    ],
    "f0c57cd0": [
      6
    ],
    "635530d2": [
      6
    ],
    "640d1ae8": [
      6
    ]
  },
  "assetsMapping": {
    "004d6765b851bbe856e8.js": "2aff1868",
    "6b958a0539ca8f1b95a1.js": "6234ee3c",
    "8f762cbe7a4a96469ce2.js": "1a3ae26b",
    "ae5edfd4a045906f5a5e.js": "2a130dde",
    "c4388af5d0d36905bbfc.js": "7ea1d828",
    "cb29d40efca0f98d54f9.js": "2cc458b6",
    "f18ab47b0c8600674e6a.js": "0859c165",
    "fa0c48a5b5a17ed787cd.js": "6fca0322"
  }
}